Metadata-Version: 2.1
Name: pianoviewer
Version: 0.0.2
Summary: Displays key presses from MIDI.
Home-page: https://git.brokenmouse.studio/ever/pianoviewer
Author: EV3R4
License: MIT
Keywords: midi,piano
Platform: UNKNOWN
Classifier: Development Status :: 3 - Alpha
Classifier: Intended Audience :: End Users/Desktop
Classifier: Topic :: Multimedia :: Sound/Audio :: MIDI
Classifier: Topic :: Utilities
Classifier: License :: OSI Approved :: MIT License
Classifier: Programming Language :: Python :: 3
Classifier: Programming Language :: Python :: 3.8
Classifier: Operating System :: OS Independent
Classifier: Natural Language :: English
Requires-Python: >=3.8
